{"skeleton":{"hash":"nCrA+MA1jBGcfL8VAP983aIMjJ8","spine":"3.8.99","x":-44.21,"y":-39.83,"width":88.29,"height":79.41,"images":"./images/","audio":""},"bones":[{"name":"root"},{"name":"bone","parent":"root"},{"name":"icon_gift_01","parent":"bone","length":22.11,"rotation":360,"x":-13.23,"y":-6.24},{"name":"icon_gift_02","parent":"bone","length":17.41,"rotation":72.47,"x":12.99,"y":-15.41}],"slots":[{"name":"icon_gift_01","bone":"icon_gift_01","attachment":"icon_gift_01"},{"name":"icon_gift_02","bone":"icon_gift_02","attachment":"icon_gift_02"}],"skins":[{"name":"default","attachments":{"icon_gift_01":{"icon_gift_01":{"x":-2.97,"y":11.82,"width":56,"height":68}},"icon_gift_02":{"icon_gift_02":{"x":10.07,"y":-0.07,"rotation":-72.47,"width":56,"height":68}}}}],"animations":{"animation":{"bones":{"icon_gift_01":{"rotate":[{"angle":-6.37,"curve":0.25,"c3":0.75},{"time":0.5,"angle":11.8,"curve":0.25,"c3":0.75},{"time":1,"angle":-6.37}],"translate":[{}]},"icon_gift_02":{"rotate":[{"angle":-2.69,"curve":0.38,"c2":0.59,"c3":0.727},{"time":0.1333,"angle":-6.37,"curve":0.25,"c3":0.75},{"time":0.6333,"angle":11.8,"curve":0.242,"c3":0.663,"c4":0.65},{"time":1,"angle":-2.69}]}}}}}